{
  "aa": "aar",
  "aar": "aar",
  "ab": "abk",
  "abchasisch": "abk",
  "abk": "abk",
  "abkhaze": "abk",
  "abkhazian": "abk",
  "ace": "ace",
  "aceh": "ace",
  "aceh-sprache": "ace",
  "ach": "ach",
  "achinese": "ace",
  "acholi-sprache": "ach",
  "acoli": "ach",
  "ada": "ada",
  "adangme": "ada",
  "adangme-sprache": "ada",
  "ady": "ady",
  "adygei": "ady",
  "adyghe": "ady",
  "adyghé": "ady",
  "adygisch": "ady",
  "ae": "ave",
  "af": "afr",
  "afa": "afa",
  "afar": "aar",
  "afh": "afh",
  "afr": "afr",
  "afrihili": "afh",
  "afrikaans": "afr",
  "afro-asiatic languages": "afa",
  "afro-asiatiques, langues": "afa",
  "ain": "ain",
  "ainu": "ain",
  "ainu-sprache": "ain",
  "ak": "aka",
  "aka": "aka",
  "akan": "aka",
  "akan-sprache": "aka",
  "akk": "akk",
  "akkadian": "akk",
  "akkadien": "akk",
  "akkadisch": "akk",
  "alb": "alb",
  "albanais": "alb",
  "albanian": "alb",
  "albanisch": "alb",
  "ale": "ale",
  "alemannic": "gsw",
  "aleut": "ale",
  "aleutisch": "ale",
  "alg": "alg",
  "algonkin-sprachen (andere)": "alg",
  "algonquian languages": "alg",
  "algonquines, langues": "alg",
  "allemand": "ger",
  "allemand, bas": "nds",
  "allemand, moyen haut (ca. 1050-1500)": "gmh",
  "allemand, vieux haut (ca. 750-1050)": "goh",
  "alsacien": "gsw",
  "alsatian": "gsw",
  "alt": "alt",
  "alt-newari": "nwc",
  "altai du sud": "alt",
  "altaic languages": "tut",
  "altaisch": "alt",
  "altaische sprachen (andere)": "tut",
  "altaïques, langues": "tut",
  "altenglisch": "ang",
  "altfranzösisch": "fro",
  "althochdeutsch": "goh",
  "altirisch": "sga",
  "altnorwegisch": "non",
  "altokzitanisch": "pro",
  "altpersisch": "peo",
  "altäthiopisch": "gez",
  "alémanique": "gsw",
  "aléoute": "ale",
  "am": "amh",
  "amazighe standard marocain": "zgh",
  "amh": "amh",
  "amharic": "amh",
  "amharique": "amh",
  "amharisch": "amh",
  "amérindiennes de l'amérique centrale, langues": "cai",
  "an": "arg",
  "ang": "ang",
  "anga-sprache": "anp",
  "angika": "anp",
  "anglais": "eng",
  "anglais moyen (1100-1500)": "enm",
  "anglo-saxon (ca.450-1100)": "ang",
  "anp": "anp",
  "apa": "apa",
  "apache languages": "apa",
  "apachen-sprachen": "apa",
  "apaches, langues": "apa",
  "ar": "ara",
  "ara": "ara",
  "arabe": "ara",
  "arabic": "ara",
  "arabisch": "ara",
  "aragonais": "arg",
  "aragonese": "arg",
  "aragonesisch": "arg",
  "aramäisch": "arc",
  "araméen d'empire (700-300 bce)": "arc",
  "arapaho": "arp",
  "arapaho-sprache": "arp",
  "arauka-sprachen": "arn",
  "arawak": "arw",
  "arawak-sprachen": "arw",
  "arc": "arc",
  "arg": "arg",
  "arm": "arm",
  "armenian": "arm",
  "armenisch": "arm",
  "arménien": "arm",
  "arn": "arn",
  "aromanian": "rup",
  "aromunisch": "rup",
  "aroumain": "rup",
  "arp": "arp",
  "art": "art",
  "artificial languages": "art",
  "artificielles, langues": "art",
  "arumanian": "rup",
  "arw": "arw",
  "as": "asm",
  "aserbeidschanisch": "aze",
  "asm": "asm",
  "assamais": "asm",
  "assamese": "asm",
  "assamesisch": "asm",
  "ast": "ast",
  "asturian": "ast",
  "asturien": "ast",
  "asturisch": "ast",
  "asturleonese": "ast",
  "asturoléonais": "ast",
  "ath": "ath",
  "athapascan languages": "ath",
  "athapascanes, langues": "ath",
  "athapaskische sprachen (andere)": "ath",
  "aus": "aus",
  "australian languages": "aus",
  "australiennes, langues": "aus",
  "australische sprachen": "aus",
  "austronesian languages": "map",
  "austronesische sprachen (andere)": "map",
  "austronésiennes, langues": "map",
  "av": "ava",
  "ava": "ava",
  "avar": "ava",
  "avaric": "ava",
  "ave": "ave",
  "avestan": "ave",
  "avestique": "ave",
  "avestisch": "ave",
  "awa": "awa",
  "awadhi": "awa",
  "awarisch": "ava",
  "ay": "aym",
  "aym": "aym",
  "aymara": "aym",
  "aymará-sprache": "aym",
  "az": "aze",
  "aze": "aze",
  "azerbaijani": "aze",
  "azéri": "aze",
  "aïnou": "ain",
  "ba": "bak",
  "bable": "ast",
  "bachkir": "bak",
  "bad": "bad",
  "bahasa indonesia": "ind",
  "bai": "bai",
  "bak": "bak",
  "bal": "bal",
  "balinais": "ban",
  "balinese": "ban",
  "balinesisch": "ban",
  "baloutchi": "bal",
  "baltes, langues": "bat",
  "baltic languages": "bat",
  "baltische sprachen (andere)": "bat",
  "baluchi": "bal",
  "bam": "bam",
  "bambara": "bam",
  "bambara-sprache": "bam",
  "bamileke languages": "bai",
  "bamileke-sprachen": "bai",
  "bamiléké, langues": "bai",
  "ban": "ban",
  "banda languages": "bad",
  "banda, langues": "bad",
  "banda-sprachen (ubangi-sprachen)": "bad",
  "bantou, langues": "bnt",
  "bantu languages": "bnt",
  "bantusprachen (andere)": "bnt",
  "baq": "baq",
  "bas": "bas",
  "bas allemand": "nds",
  "bas saxon": "nds",
  "bas-sorabe": "dsb",
  "basa": "bas",
  "basaa-sprache": "bas",
  "baschkirisch": "bak",
  "bashkir": "bak",
  "baskisch": "baq",
  "basque": "baq",
  "bat": "bat",
  "batak languages": "btk",
  "batak, langues": "btk",
  "batak-sprache": "btk",
  "be": "bel",
  "beach-la-mar": "bis",
  "bedauye": "bej",
  "bedawiyet": "bej",
  "bedja": "bej",
  "bej": "bej",
  "beja": "bej",
  "bel": "bel",
  "belarusian": "bel",
  "belutschisch": "bal",
  "bem": "bem",
  "bemba": "bem",
  "bemba-sprache": "bem",
  "ben": "ben",
  "bengali": "ben",
  "ber": "ber",
  "berber languages": "ber",
  "berbersprachen (andere)": "ber",
  "berbères, langues": "ber",
  "bg": "bul",
  "bh": "bih",
  "bho": "bho",
  "bhojpuri": "bho",
  "bi": "bis",
  "bichlamar": "bis",
  "bih": "bih",
  "bihari (andere)": "bih",
  "bihari languages": "bih",
  "bik": "bik",
  "bikol": "bik",
  "bikol-sprache": "bik",
  "bilen": "byn",
  "bilin": "byn",
  "bilin-sprache": "byn",
  "bin": "bin",
  "bini": "bin",
  "birman": "bur",
  "birmanisch": "bur",
  "bis": "bis",
  "bislama": "bis",
  "biélorusse": "bel",
  "bla": "bla",
  "blackfoot": "bla",
  "blackfoot-sprache": "bla",
  "blin": "byn",
  "bliss": "zbl",
  "bliss-symbol": "zbl",
  "blissymbolics": "zbl",
  "blissymbols": "zbl",
  "bm": "bam",
  "bn": "ben",
  "bnt": "bnt",
  "bo": "tib",
  "bod": "tib",
  "bokmål": "nob",
  "bokmål, norwegian": "nob",
  "bos": "bos",
  "bosnian": "bos",
  "bosniaque": "bos",
  "bosnisch": "bos",
  "bouriate": "bua",
  "br": "bre",
  "bra": "bra",
  "braj": "bra",
  "braj-bhakha": "bra",
  "bre": "bre",
  "breton": "bre",
  "bretonisch": "bre",
  "bs": "bos",
  "btk": "btk",
  "bua": "bua",
  "bug": "bug",
  "bugi": "bug",
  "bugi-sprache": "bug",
  "buginese": "bug",
  "bul": "bul",
  "bulgare": "bul",
  "bulgarian": "bul",
  "bulgarisch": "bul",
  "bur": "bur",
  "buriat": "bua",
  "burjatisch": "bua",
  "burmese": "bur",
  "byn": "byn",
  "ca": "cat",
  "cad": "cad",
  "caddo": "cad",
  "caddo-sprachen": "cad",
  "cai": "cai",
  "car": "car",
  "carib": "car",
  "carélien": "krl",
  "castilian": "spa",
  "castillan": "spa",
  "cat": "cat",
  "catalan": "cat",
  "cau": "cau",
  "caucasian languages": "cau",
  "caucasiennes, langues": "cau",
  "ce": "che",
  "ceb": "ceb",
  "cebuano": "ceb",
  "cel": "cel",
  "celtes, langues": "cel",
  "celtic languages": "cel",
  "celtiques, langues": "cel",
  "central american indian languages": "cai",
  "central khmer": "khm",
  "ces": "cze",
  "ch": "cha",
  "cha": "cha",
  "chagatai": "chg",
  "cham-sprachen": "cmc",
  "chames, langues": "cmc",
  "chamic languages": "cmc",
  "chamorro": "cha",
  "chamorro-sprache": "cha",
  "chan": "shn",
  "chb": "chb",
  "che": "che",
  "chechen": "che",
  "cherokee": "chr",
  "cherokee-sprache": "chr",
  "chewa": "nya",
  "cheyenne": "chy",
  "cheyenne-sprache": "chy",
  "chg": "chg",
  "chi": "chi",
  "chibcha": "chb",
  "chibcha-sprachen": "chb",
  "chichewa": "nya",
  "chinese": "chi",
  "chinesisch": "chi",
  "chinois": "chi",
  "chinook jargon": "chn",
  "chinook, jargon": "chn",
  "chinook-jargon": "chn",
  "chipewyan": "chp",
  "chipewyan-sprache": "chp",
  "chk": "chk",
  "chm": "chm",
  "chn": "chn",
  "cho": "cho",
  "choctaw": "cho",
  "choctaw-sprache": "cho",
  "chp": "chp",
  "chr": "chr",
  "chu": "chu",
  "chuang": "zha",
  "church slavic": "chu",
  "church slavonic": "chu",
  "chuuk": "chk",
  "chuukese": "chk",
  "chuvash": "chv",
  "chv": "chv",
  "chy": "chy",
  "classical nepal bhasa": "nwc",
  "classical newari": "nwc",
  "classical syriac": "syc",
  "cmc": "cmc",
  "cnr": "cnr",
  "co": "cos",
  "cook islands maori": "rar",
  "cop": "cop",
  "copte": "cop",
  "coptic": "cop",
  "cor": "cor",
  "cornique": "cor",
  "cornish": "cor",
  "corse": "cos",
  "corsican": "cos",
  "coréen": "kor",
  "cos": "cos",
  "couchitiques, langues": "cus",
  "cpe": "cpe",
  "cpf": "cpf",
  "cpp": "cpp",
  "cr": "cre",
  "cre": "cre",
  "cree": "cre",
  "cree-sprache": "cre",
  "creek": "mus",
  "creoles and pidgins": "crp",
  "creoles and pidgins, english based": "cpe",
  "creoles and pidgins, french-based": "cpf",
  "creoles and pidgins, portuguese-based": "cpp",
  "crh": "crh",
  "crimean tatar": "crh",
  "crimean turkish": "crh",
  "croate": "hrv",
  "croatian": "hrv",
  "crp": "crp",
  "créole haïtien": "hat",
  "créoles et pidgins": "crp",
  "créoles et pidgins basés sur l'anglais": "cpe",
  "créoles et pidgins basés sur le français": "cpf",
  "créoles et pidgins basés sur le portugais": "cpp",
  "cs": "cze",
  "csb": "csb",
  "cu": "chu",
  "cus": "cus",
  "cushitic languages": "cus",
  "cv": "chv",
  "cy": "wel",
  "cym": "wel",
  "cze": "cze",
  "czech": "cze",
  "da": "dan",
  "dajakisch": "day",
  "dak": "dak",
  "dakota": "dak",
  "dakota-sprache": "dak",
  "dan": "dan",
  "danakil-sprache": "aar",
  "danish": "dan",
  "danois": "dan",
  "dar": "dar",
  "darginisch": "dar",
  "dargwa": "dar",
  "day": "day",
  "dayak, langues": "day",
  "de": "ger",
  "del": "del",
  "delaware": "del",
  "delaware-sprache": "del",
  "den": "den",
  "dene suline": "chp",
  "deu": "ger",
  "deutsch": "ger",
  "dgr": "dgr",
  "dhivehi": "div",
  "dimili": "zza",
  "dimli": "zza",
  "din": "din",
  "dinka": "din",
  "dinka-sprache": "din",
  "dioula": "dyu",
  "div": "div",
  "divehi": "div",
  "djaghataï": "chg",
  "dogri": "doi",
  "dogrib": "dgr",
  "dogrib-sprache": "dgr",
  "doi": "doi",
  "douala": "dua",
  "dra": "dra",
  "dravidian languages": "dra",
  "dravidiennes, langues": "dra",
  "drawidische sprachen (andere)": "dra",
  "dsb": "dsb",
  "dua": "dua",
  "duala": "dua",
  "duala-sprachen": "dua",
  "dum": "dum",
  "dut": "dut",
  "dutch": "dut",
  "dutch, middle": "dum",
  "dutch, middle (ca.1050-1350)": "dum",
  "dv": "div",
  "dyu": "dyu",
  "dyula": "dyu",
  "dyula-sprache": "dyu",
  "dz": "dzo",
  "dzo": "dzo",
  "dzongkha": "dzo",
  "dänisch": "dan",
  "eastern frisian": "frs",
  "edo": "bin",
  "edo-sprache": "bin",
  "ee": "ewe",
  "efi": "efi",
  "efik": "efi",
  "egy": "egy",
  "egyptian": "egy",
  "egyptian (ancient)": "egy",
  "einzelne andere sprachen": "mis",
  "eka": "eka",
  "ekajuk": "eka",
  "el": "gre",
  "elamisch": "elx",
  "elamite": "elx",
  "ell": "gre",
  "elliceanisch": "tvl",
  "elx": "elx",
  "en": "eng",
  "eng": "eng",
  "englisch": "eng",
  "english": "eng",
  "english, middle": "enm",
  "english, middle (1100-1500)": "enm",
  "english, old": "ang",
  "english, old (ca.450-1100)": "ang",
  "enm": "enm",
  "eo": "epo",
  "epo": "epo",
  "erza": "myv",
  "erza-mordwinisch": "myv",
  "erzya": "myv",
  "es": "spa",
  "esclave (athapascan)": "den",
  "espagnol": "spa",
  "esperanto": "epo",
  "espéranto": "epo",
  "est": "est",
  "estnisch": "est",
  "estonian": "est",
  "estonien": "est",
  "et": "est",
  "eu": "baq",
  "eus": "baq",
  "ewe": "ewe",
  "ewe-sprache": "ewe",
  "ewo": "ewo",
  "ewondo": "ewo",
  "fa": "per",
  "fan": "fan",
  "fang": "fan",
  "fante-sprache": "fat",
  "fanti": "fat",
  "fao": "fao",
  "faroese": "fao",
  "fas": "per",
  "fat": "fat",
  "ff": "ful",
  "fi": "fin",
  "fidjien": "fij",
  "fidschi-sprache": "fij",
  "fij": "fij",
  "fijian": "fij",
  "fil": "fil",
  "filipino": "fil",
  "fin": "fin",
  "finnisch": "fin",
  "finnish": "fin",
  "finno-ougriennes, langues": "fiu",
  "finno-ugrian languages": "fiu",
  "finnois": "fin",
  "finnougrische sprachen (andere)": "fiu",
  "fiu": "fiu",
  "fj": "fij",
  "flamand": "dut",
  "flemish": "dut",
  "fo": "fao",
  "fon": "fon",
  "fon-sprache": "fon",
  "fr": "fre",
  "fra": "fre",
  "französisch": "fre",
  "français": "fre",
  "français ancien (842-ca.1400)": "fro",
  "français moyen (1400-1600)": "frm",
  "fre": "fre",
  "french": "fre",
  "french, middle": "frm",
  "french, middle (ca.1400-1600)": "frm",
  "french, old": "fro",
  "french, old (842-ca.1400)": "fro",
  "friesisch": "fry",
  "frioulan": "fur",
  "frison occidental": "fry",
  "frison oriental": "frs",
  "frison septentrional": "frr",
  "friulian": "fur",
  "friulisch": "fur",
  "frm": "frm",
  "fro": "fro",
  "frr": "frr",
  "frs": "frs",
  "fry": "fry",
  "ful": "ful",
  "fulah": "ful",
  "fur": "fur",
  "fy": "fry",
  "färöisch": "fao",
  "féroïen": "fao",
  "ga": "gle",
  "ga-sprache": "gaa",
  "gaa": "gaa",
  "gaelic": "gla",
  "galibi": "car",
  "galibi carib": "car",
  "galician": "glg",
  "galicien": "glg",
  "galicisch": "glg",
  "galla": "orm",
  "galla-sprache": "orm",
  "gallois": "wel",
  "ganda": "lug",
  "ganda-sprache": "lug",
  "gay": "gay",
  "gayo": "gay",
  "gayo-sprache": "gay",
  "gaélique": "gla",
  "gaélique écossais": "gla",
  "gba": "gba",
  "gbaya": "gba",
  "gbaya-sprache": "gba",
  "gd": "gla",
  "geez": "gez",
  "gem": "gem",
  "geo": "geo",
  "georgian": "geo",
  "georgisch": "geo",
  "ger": "ger",
  "german": "ger",
  "german, low": "nds",
  "german, middle high": "gmh",
  "german, middle high (ca.1050-1500)": "gmh",
  "german, old high": "goh",
  "german, old high (ca.750-1050)": "goh",
  "germanic languages": "gem",
  "germaniques, langues": "gem",
  "germanische sprachen (andere)": "gem",
  "gez": "gez",
  "gikuyu": "kik",
  "gil": "gil",
  "gilbertese": "gil",
  "gilbertesisch": "gil",
  "gl": "glg",
  "gla": "gla",
  "gle": "gle",
  "glg": "glg",
  "glv": "glv",
  "gmh": "gmh",
  "gn": "grn",
  "goh": "goh",
  "gon": "gon",
  "gond": "gon",
  "gondi": "gon",
  "gondi-sprache": "gon",
  "gor": "gor",
  "gorontalesisch": "gor",
  "gorontalo": "gor",
  "got": "got",
  "gothic": "got",
  "gothique": "got",
  "gotisch": "got",
  "goudjrati": "guj",
  "grb": "grb",
  "grc": "grc",
  "gre": "gre",
  "grebo": "grb",
  "grebo-sprache": "grb",
  "grec ancien (jusqu'à 1453)": "grc",
  "grec moderne (après 1453)": "gre",
  "greek": "gre",
  "greek, ancient": "grc",
  "greek, ancient (to 1453)": "grc",
  "greek, modern": "gre",
  "greek, modern (1453-)": "gre",
  "greenlandic": "kal",
  "griechisch": "grc",
  "grn": "grn",
  "groenlandais": "kal",
  "grönländisch": "kal",
  "gsw": "gsw",
  "gu": "guj",
  "guarani": "grn",
  "guaraní-sprache": "grn",
  "guj": "guj",
  "gujarati": "guj",
  "gujarati-sprache": "guj",
  "guèze": "gez",
  "gv": "glv",
  "gwi": "gwi",
  "gwich'in": "gwi",
  "gälisch-schottisch": "gla",
  "géorgien": "geo",
  "ha": "hau",
  "hai": "hai",
  "haida": "hai",
  "haida-sprache": "hai",
  "haitian": "hat",
  "haitian creole": "hat",
  "hamitosemitische sprachen (andere)": "afa",
  "haoussa": "hau",
  "hat": "hat",
  "hau": "hau",
  "hausa": "hau",
  "haussa-sprache": "hau",
  "haut-sorabe": "hsb",
  "haw": "haw",
  "hawaiian": "haw",
  "hawaiisch": "haw",
  "hawaïen": "haw",
  "haïtien": "hat",
  "haïtien (haiti-kreolisch)": "hat",
  "he": "heb",
  "heb": "heb",
  "hebrew": "heb",
  "hebräisch": "heb",
  "her": "her",
  "herero": "her",
  "herero-sprache": "her",
  "hethitisch": "hit",
  "hi": "hin",
  "hil": "hil",
  "hiligaynon": "hil",
  "hiligaynon-sprache": "hil",
  "him": "him",
  "himachali": "him",
  "himachali languages": "him",
  "hin": "hin",
  "hindi": "hin",
  "hiri motu": "hmo",
  "hiri-motu": "hmo",
  "hit": "hit",
  "hittite": "hit",
  "hmn": "hmn",
  "hmo": "hmo",
  "hmong": "hmn",
  "ho": "hmo",
  "hongrois": "hun",
  "hr": "hrv",
  "hrv": "hrv",
  "hsb": "hsb",
  "ht": "hat",
  "hu": "hun",
  "hun": "hun",
  "hungarian": "hun",
  "hup": "hup",
  "hupa": "hup",
  "hupa-sprache": "hup",
  "hy": "arm",
  "hye": "arm",
  "hz": "her",
  "hébreu": "heb",
  "ia": "ina",
  "iakoute": "sah",
  "iba": "iba",
  "iban": "iba",
  "iban-sprache": "iba",
  "ibo": "ibo",
  "ibo-sprache": "ibo",
  "ice": "ice",
  "icelandic": "ice",
  "id": "ind",
  "ido": "ido",
  "ie": "ile",
  "ig": "ibo",
  "igbo": "ibo",
  "ii": "iii",
  "iii": "iii",
  "ijo": "ijo",
  "ijo languages": "ijo",
  "ijo, langues": "ijo",
  "ijo-sprache": "ijo",
  "ik": "ipk",
  "iku": "iku",
  "ile": "ile",
  "ilo": "ilo",
  "ilocano": "ilo",
  "ilokano-sprache": "ilo",
  "iloko": "ilo",
  "imperial aramaic": "arc",
  "imperial aramaic (700-300 bce)": "arc",
  "ina": "ina",
  "inari sami": "smn",
  "inarisaamisch": "smn",
  "inc": "inc",
  "ind": "ind",
  "indianersprachen, nordamerika (andere)": "nai",
  "indianersprachen, südamerika (andere)": "sai",
  "indianersprachen, zentralamerika (andere)": "cai",
  "indic languages": "inc",
  "indo-aryennes, langues": "inc",
  "indo-european languages": "ine",
  "indo-européennes, langues": "ine",
  "indoarische sprachen (andere)": "inc",
  "indogermanische sprachen (andere)": "ine",
  "indonesian": "ind",
  "indonésien": "ind",
  "indéterminée": "und",
  "ine": "ine",
  "ingouche": "inh",
  "inguschisch": "inh",
  "ingush": "inh",
  "inh": "inh",
  "interlingua": "ina",
  "interlingua (international auxiliary language association)": "ina",
  "interlingua (langue auxiliaire internationale)": "ina",
  "interlingue": "ile",
  "inuktitut": "iku",
  "inupiaq": "ipk",
  "inupik": "ipk",
  "io": "ido",
  "ipk": "ipk",
  "ira": "ira",
  "iranian languages": "ira",
  "iraniennes, langues": "ira",
  "iranische sprachen (andere)": "ira",
  "irisch": "gle",
  "irish": "gle",
  "irish, middle": "mga",
  "irish, middle (900-1200)": "mga",
  "irish, old": "sga",
  "irish, old (to 900)": "sga",
  "irlandais": "gle",
  "irlandais ancien (jusqu'à 900)": "sga",
  "irlandais moyen (900-1200)": "mga",
  "iro": "iro",
  "irokesische sprachen": "iro",
  "iroquoian languages": "iro",
  "iroquoises, langues": "iro",
  "is": "ice",
  "isl": "ice",
  "islandais": "ice",
  "isländisch": "ice",
  "it": "ita",
  "ita": "ita",
  "italian": "ita",
  "italien": "ita",
  "italienisch": "ita",
  "iu": "iku",
  "ja": "jpn",
  "jakutisch": "sah",
  "japanese": "jpn",
  "japanisch": "jpn",
  "japonais": "jpn",
  "jav": "jav",
  "javanais": "jav",
  "javanese": "jav",
  "javanisch": "jav",
  "jbo": "jbo",
  "jiddisch": "yid",
  "jingpho": "kac",
  "jpn": "jpn",
  "jpr": "jpr",
  "jrb": "jrb",
  "judenspanisch": "lad",
  "judeo-arabic": "jrb",
  "judeo-persian": "jpr",
  "judéo-arabe": "jrb",
  "judéo-espagnol": "lad",
  "judéo-persan": "jpr",
  "jv": "jav",
  "jüdisch-arabisch": "jrb",
  "jüdisch-persisch": "jpr",
  "ka": "geo",
  "kaa": "kaa",
  "kab": "kab",
  "kabardian": "kbd",
  "kabardien": "kbd",
  "kabardinisch": "kbd",
  "kabyle": "kab",
  "kabylisch": "kab",
  "kac": "kac",
  "kachin": "kac",
  "kachin-sprache": "kac",
  "kachoube": "csb",
  "kal": "kal",
  "kalaallisut": "kal",
  "kalmouk": "xal",
  "kalmyk": "xal",
  "kalmückisch": "xal",
  "kam": "kam",
  "kamba": "kam",
  "kamba-sprache": "kam",
  "kambodschanisch": "khm",
  "kan": "kan",
  "kannada": "kan",
  "kanouri": "kau",
  "kanuri": "kau",
  "kanuri-sprache": "kau",
  "kapampangan": "pam",
  "kar": "kar",
  "kara-kalpak": "kaa",
  "karachay-balkar": "krc",
  "karakalpak": "kaa",
  "karakalpakisch": "kaa",
  "karatchai balkar": "krc",
  "karatschaiisch-balkarisch": "krc",
  "karelian": "krl",
  "karelisch": "krl",
  "karen languages": "kar",
  "karen, langues": "kar",
  "karenisch": "kar",
  "karib": "car",
  "karibische sprachen": "car",
  "kas": "kas",
  "kasachisch": "kaz",
  "kaschmiri": "kas",
  "kaschubisch": "csb",
  "kashmiri": "kas",
  "kashubian": "csb",
  "kat": "geo",
  "katalanisch": "cat",
  "kau": "kau",
  "kaukasische sprachen (andere)": "cau",
  "kaw": "kaw",
  "kawi": "kaw",
  "kaz": "kaz",
  "kazakh": "kaz",
  "kbd": "kbd",
  "kein linguistischer inhalt": "zxx",
  "keltische sprachen (andere)": "cel",
  "kg": "kon",
  "kha": "kha",
  "khasi": "kha",
  "khasi-sprache": "kha",
  "khi": "khi",
  "khm": "khm",
  "khmer central": "khm",
  "kho": "kho",
  "khoisan languages": "khi",
  "khoisan-sprachen (andere)": "khi",
  "khotanais": "kho",
  "khotanese": "kho",
  "khotta": "mag",
  "khoïsan, langues": "khi",
  "ki": "kik",
  "kik": "kik",
  "kikuyu": "kik",
  "kikuyu-sprache": "kik",
  "kimbundu": "kmb",
  "kimbundu-sprache": "kmb",
  "kin": "kin",
  "kinyarwanda": "kin",
  "kir": "kir",
  "kirchenslawisch": "chu",
  "kirdki": "zza",
  "kirghiz": "kir",
  "kirgisisch": "kir",
  "kiribati": "gil",
  "kirmanjki": "zza",
  "kj": "kua",
  "kk": "kaz",
  "kl": "kal",
  "klingon": "tlh",
  "klingonisch": "tlh",
  "km": "khm",
  "kmb": "kmb",
  "kn": "kan",
  "ko": "kor",
  "kok": "kok",
  "kom": "kom",
  "komi": "kom",
  "komi-sprache": "kom",
  "kon": "kon",
  "kongo": "kon",
  "kongo-sprache": "kon",
  "konkani": "kok",
  "koptisch": "cop",
  "kor": "kor",
  "korean": "kor",
  "koreanisch": "kor",
  "kornisch": "cor",
  "korsisch": "cos",
  "kos": "kos",
  "kosrae": "kos",
  "kosraean": "kos",
  "kosraeanisch": "kos",
  "koumyk": "kum",
  "kpe": "kpe",
  "kpelle": "kpe",
  "kpelle-sprache": "kpe",
  "kpellé": "kpe",
  "kr": "kau",
  "krc": "krc",
  "kreolisch-englisch (andere)": "cpe",
  "kreolisch-französisch (andere)": "cpf",
  "kreolisch-portugiesisch (andere)": "cpp",
  "kreolische sprachen": "crp",
  "krimtatarisch": "crh",
  "krl": "krl",
  "kro": "kro",
  "kroatisch": "hrv",
  "krou, langues": "kro",
  "kru": "kru",
  "kru languages": "kro",
  "kru-sprachen (andere)": "kro",
  "ks": "kas",
  "ku": "kur",
  "kua": "kua",
  "kuanyama": "kua",
  "kum": "kum",
  "kumyk": "kum",
  "kumükisch": "kum",
  "kunstsprachen (andere)": "art",
  "kur": "kur",
  "kurde": "kur",
  "kurdisch": "kur",
  "kurdish": "kur",
  "kurukh": "kru",
  "kuschitische sprachen (andere)": "cus",
  "kut": "kut",
  "kutchin-sprache": "gwi",
  "kutenai": "kut",
  "kutenai-sprache": "kut",
  "kv": "kom",
  "kw": "cor",
  "kwanyama": "kua",
  "kwanyama-sprache": "kua",
  "ky": "kir",
  "kymrisch": "wel",
  "kyrgyz": "kir",
  "la": "lat",
  "lad": "lad",
  "ladino": "lad",
  "lah": "lah",
  "lahnda": "lah",
  "lalo-sprache": "iii",
  "lam": "lam",
  "lamba": "lam",
  "lamba-sprache (bantusprache)": "lam",
  "land dayak languages": "day",
  "langues biharis": "bih",
  "langues des signes": "sgn",
  "langues himachalis": "him",
  "langues non codées": "mis",
  "langues paharis occidentales": "him",
  "lao": "lao",
  "laotisch": "lao",
  "lat": "lat",
  "latein": "lat",
  "latin": "lat",
  "latvian": "lav",
  "lav": "lav",
  "lb": "ltz",
  "leonese": "ast",
  "lesgisch": "lez",
  "lettisch": "lav",
  "letton": "lav",
  "letzeburgesch": "ltz",
  "lez": "lez",
  "lezghian": "lez",
  "lezghien": "lez",
  "lg": "lug",
  "li": "lim",
  "lim": "lim",
  "limbourgeois": "lim",
  "limburgan": "lim",
  "limburger": "lim",
  "limburgisch": "lim",
  "limburgish": "lim",
  "lin": "lin",
  "lingala": "lin",
  "lit": "lit",
  "litauisch": "lit",
  "lithuanian": "lit",
  "lituanien": "lit",
  "ln": "lin",
  "lo": "lao",
  "lojban": "jbo",
  "lol": "lol",
  "low german": "nds",
  "low saxon": "nds",
  "lower sorbian": "dsb",
  "loz": "loz",
  "lozi": "loz",
  "lt": "lit",
  "ltz": "ltz",
  "lu": "lub",
  "lua": "lua",
  "lub": "lub",
  "luba-katanga": "lub",
  "luba-katanga-sprache": "lub",
  "luba-lulua": "lua",
  "lug": "lug",
  "lui": "lui",
  "luiseno": "lui",
  "luiseño-sprache": "lui",
  "lule sami": "smj",
  "lulesaamisch": "smj",
  "lulua-sprache": "lua",
  "lun": "lun",
  "lunda": "lun",
  "lunda-sprache": "lun",
  "luo": "luo",
  "luo (kenya and tanzania)": "luo",
  "luo (kenya et tanzanie)": "luo",
  "luo-sprache": "luo",
  "lus": "lus",
  "lushai": "lus",
  "lushai-sprache": "lus",
  "luxembourgeois": "ltz",
  "luxembourgish": "ltz",
  "luxemburgisch": "ltz",
  "lv": "lav",
  "léonais": "ast",
  "mac": "mac",
  "macedo-romanian": "rup",
  "macedonian": "mac",
  "macédo-roumain": "rup",
  "macédonien": "mac",
  "mad": "mad",
  "madourais": "mad",
  "madurese": "mad",
  "maduresisch": "mad",
  "mag": "mag",
  "magahi": "mag",
  "mah": "mah",
  "mai": "mai",
  "maithili": "mai",
  "mak": "mak",
  "makasar": "mak",
  "makassar": "mak",
  "makassarisch": "mak",
  "makedonisch": "mac",
  "mal": "mal",
  "malagassi-sprache": "mlg",
  "malagasy": "mlg",
  "malaiisch": "may",
  "malais": "may",
  "malay": "may",
  "malayalam": "mal",
  "maldivian": "div",
  "maldivien": "div",
  "maledivisch": "div",
  "malgache": "mlg",
  "malinke-sprache": "man",
  "maltais": "mlt",
  "maltese": "mlt",
  "maltesisch": "mlt",
  "man": "man",
  "manchu": "mnc",
  "mandar": "mdr",
  "mandaresisch": "mdr",
  "mandchou": "mnc",
  "mandingo": "man",
  "mandingue": "man",
  "mandschurisch": "mnc",
  "manipuri": "mni",
  "mannois": "glv",
  "manobo languages": "mno",
  "manobo, langues": "mno",
  "manobo-sprachen": "mno",
  "manx": "glv",
  "mao": "mao",
  "maori": "mao",
  "maori des îles cook": "rar",
  "maori-sprache": "mao",
  "map": "map",
  "mapuce": "arn",
  "mapuche": "arn",
  "mapudungun": "arn",
  "mar": "mar",
  "marathe": "mar",
  "marathi": "mar",
  "mari": "chm",
  "marschallesisch": "mah",
  "marshall": "mah",
  "marshallese": "mah",
  "marvari": "mwr",
  "marwari": "mwr",
  "mas": "mas",
  "masai": "mas",
  "massai-sprache": "mas",
  "massaï": "mas",
  "may": "may",
  "maya, langues": "myn",
  "maya-sprachen": "myn",
  "mayan languages": "myn",
  "mbundu-sprache": "umb",
  "mdf": "mdf",
  "mdr": "mdr",
  "mehrere sprachen": "mul",
  "meithei-sprache": "mni",
  "men": "men",
  "mende": "men",
  "mende-sprache": "men",
  "mendé": "men",
  "mg": "mlg",
  "mga": "mga",
  "mh": "mah",
  "mi": "mao",
  "mi'kmaq": "mic",
  "miao-sprachen": "hmn",
  "mic": "mic",
  "micmac": "mic",
  "micmac-sprache": "mic",
  "min": "min",
  "minangkabau": "min",
  "minangkabau-sprache": "min",
  "mirandais": "mwl",
  "mirandese": "mwl",
  "mirandesisch": "mwl",
  "mis": "mis",
  "mittelenglisch": "enm",
  "mittelfranzösisch": "frm",
  "mittelhochdeutsch": "gmh",
  "mittelirisch": "mga",
  "mittelniederländisch": "dum",
  "mittelpersisch": "pal",
  "mk": "mac",
  "mkd": "mac",
  "mkh": "mkh",
  "ml": "mal",
  "mlg": "mlg",
  "mlt": "mlt",
  "mn": "mon",
  "mnc": "mnc",
  "mni": "mni",
  "mno": "mno",
  "moh": "moh",
  "mohawk": "moh",
  "mohawk-sprache": "moh",
  "moksa": "mdf",
  "mokscha-sprache": "mdf",
  "moksha": "mdf",
  "moldave": "rum",
  "moldavian": "rum",
  "moldovan": "rum",
  "mon": "mon",
  "mon-khmer languages": "mkh",
  "mon-khmer-sprachen (andere)": "mkh",
  "mong": "hmn",
  "mongo": "lol",
  "mongo-sprache": "lol",
  "mongol": "mon",
  "mongolian": "mon",
  "mongolisch": "mon",
  "montenegrin": "cnr",
  "montenegrinisch": "cnr",
  "monténégrin": "cnr",
  "moré": "mos",
  "mos": "mos",
  "mossi": "mos",
  "mossi-sprache": "mos",
  "mounda, langues": "mun",
  "mr": "mar",
  "mri": "mao",
  "ms": "may",
  "msa": "may",
  "mt": "mlt",
  "mul": "mul",
  "multilingue": "mul",
  "multiple languages": "mul",
  "mun": "mun",
  "munda languages": "mun",
  "mundasprachen (andere)": "mun",
  "mus": "mus",
  "muskogee": "mus",
  "muskogisch": "mus",
  "mwl": "mwl",
  "mwr": "mwr",
  "my": "bur",
  "mya": "bur",
  "myn": "myn",
  "myv": "myv",
  "môn-khmer, langues": "mkh",
  "n'ko": "nqo",
  "na": "nau",
  "nah": "nah",
  "nahuatl": "nah",
  "nahuatl languages": "nah",
  "nahuatl, langues": "nah",
  "nai": "nai",
  "nap": "nap",
  "napolitain": "nap",
  "nau": "nau",
  "nauru": "nau",
  "nauruan": "nau",
  "nauruanisch": "nau",
  "nav": "nav",
  "navaho": "nav",
  "navajo": "nav",
  "navajo-sprache": "nav",
  "nb": "nob",
  "nbl": "nbl",
  "nd": "nde",
  "nde": "nde",
  "ndebele, north": "nde",
  "ndebele, south": "nbl",
  "ndebele-sprache (simbabwe)": "nde",
  "ndebele-sprache (transvaal)": "nbl",
  "ndo": "ndo",
  "ndonga": "ndo",
  "nds": "nds",
  "ndébélé du nord": "nde",
  "ndébélé du sud": "nbl",
  "ne": "nep",
  "neapel / mundart": "nap",
  "neapolitan": "nap",
  "nep": "nep",
  "nepal bhasa": "new",
  "nepali": "nep",
  "neugriechisch": "gre",
  "neumelanesisch": "tpi",
  "neuostaramäisch": "syr",
  "new": "new",
  "newari": "new",
  "newari classique": "nwc",
  "ng": "ndo",
  "nia": "nia",
  "nias": "nia",
  "nias-sprache": "nia",
  "nic": "nic",
  "nicht zu entscheiden": "und",
  "niederdeutsch": "nds",
  "niederländisch": "dut",
  "niedersorbisch": "dsb",
  "niger-kordofanian languages": "nic",
  "nigerkordofanische sprachen (andere)": "nic",
  "nigéro-kordofaniennes, langues": "nic",
  "nilo-saharan languages": "ssa",
  "nilo-sahariennes, langues": "ssa",
  "nilosaharanische sprachen (andere)": "ssa",
  "niu": "niu",
  "niue-sprache": "niu",
  "niuean": "niu",
  "niué": "niu",
  "nkole-sprache": "nyn",
  "nl": "dut",
  "nld": "dut",
  "nn": "nno",
  "nno": "nno",
  "no": "nor",
  "no linguistic content": "zxx",
  "nob": "nob",
  "nog": "nog",
  "nogai": "nog",
  "nogaisch": "nog",
  "nogay": "nog",
  "nogaï": "nog",
  "non": "non",
  "non applicable": "zxx",
  "nor": "nor",
  "nord-amérindiennes, langues": "nai",
  "nordfriesisch": "frr",
  "nordsaamisch": "sme",
  "norrois, vieux": "non",
  "norse, old": "non",
  "north american indian languages": "nai",
  "north ndebele": "nde",
  "northern frisian": "frr",
  "northern sami": "sme",
  "northern sotho": "nso",
  "norvégien": "nor",
  "norvégien bokmål": "nob",
  "norvégien nynorsk": "nno",
  "norwegian": "nor",
  "norwegian bokmål": "nob",
  "norwegian nynorsk": "nno",
  "norwegisch": "nor",
  "not applicable": "zxx",
  "nqo": "nqo",
  "nr": "nbl",
  "nso": "nso",
  "nub": "nub",
  "nubian languages": "nub",
  "nubiennes, langues": "nub",
  "nubische sprachen": "nub",
  "nuosu": "iii",
  "nv": "nav",
  "nwc": "nwc",
  "ny": "nya",
  "nya": "nya",
  "nyamwezi": "nym",
  "nyamwezi-sprache": "nym",
  "nyanja": "nya",
  "nyanja-sprache": "nya",
  "nyankole": "nyn",
  "nyankolé": "nyn",
  "nym": "nym",
  "nyn": "nyn",
  "nynorsk": "nno",
  "nynorsk, norvégien": "nno",
  "nynorsk, norwegian": "nno",
  "nyo": "nyo",
  "nyoro": "nyo",
  "nyoro-sprache": "nyo",
  "nzema": "nzi",
  "nzi": "nzi",
  "nzima": "nzi",
  "nzima-sprache": "nzi",
  "néerlandais": "dut",
  "néerlandais moyen (ca. 1050-1350)": "dum",
  "népalais": "nep",
  "obersorbisch": "hsb",
  "oc": "oci",
  "occidental": "ile",
  "occitan": "oci",
  "occitan (après 1500)": "oci",
  "occitan (post 1500)": "oci",
  "occitan ancien (jusqu'à 1500)": "pro",
  "occitan, old": "pro",
  "occitan, old (to 1500)": "pro",
  "oci": "oci",
  "official aramaic": "arc",
  "official aramaic (700-300 bce)": "arc",
  "oirat": "xal",
  "oj": "oji",
  "oji": "oji",
  "ojibwa": "oji",
  "ojibwa-sprache": "oji",
  "okzitanisch": "oci",
  "old bulgarian": "chu",
  "old church slavonic": "chu",
  "old newari": "nwc",
  "old slavonic": "chu",
  "om": "orm",
  "or": "ori",
  "oraon-sprache": "kru",
  "ori": "ori",
  "oriya": "ori",
  "oriya-sprache": "ori",
  "orm": "orm",
  "oromo": "orm",
  "os": "oss",
  "osa": "osa",
  "osage": "osa",
  "osage-sprache": "osa",
  "osmanisch": "ota",
  "oss": "oss",
  "ossetian": "oss",
  "ossetic": "oss",
  "ossetisch": "oss",
  "ossète": "oss",
  "osterinsel-sprache": "rap",
  "ostfriesisch": "frs",
  "ota": "ota",
  "oto": "oto",
  "otomangue-sprachen": "oto",
  "otomi, langues": "oto",
  "otomian languages": "oto",
  "oudmourte": "udm",
  "ougaritique": "uga",
  "ourdou": "urd",
  "ouszbek": "uzb",
  "ouïgour": "uig",
  "oïrat": "xal",
  "pa": "pan",
  "paa": "paa",
  "pachto": "pus",
  "pag": "pag",
  "pahlavi": "pal",
  "pal": "pal",
  "palau": "pau",
  "palau-sprache": "pau",
  "palauan": "pau",
  "pali": "pli",
  "pam": "pam",
  "pampanga": "pam",
  "pampangan": "pam",
  "pampanggan-sprache": "pam",
  "pan": "pan",
  "pandschabi-sprache": "pan",
  "pangasinan": "pag",
  "pangasinan-sprache": "pag",
  "pangwe-sprache": "fan",
  "panjabi": "pan",
  "pap": "pap",
  "papiamento": "pap",
  "papoues, langues": "paa",
  "papuan languages": "paa",
  "papuasprachen (andere)": "paa",
  "pas de contenu linguistique": "zxx",
  "paschtu": "pus",
  "pashto": "pus",
  "pau": "pau",
  "pedi": "nso",
  "pedi-sprache": "nso",
  "pendjabi": "pan",
  "peo": "peo",
  "per": "per",
  "persan": "per",
  "perse, vieux (ca. 600-400 av. j.-c.)": "peo",
  "persian": "per",
  "persian, old": "peo",
  "persian, old (ca.600-400 b.c.)": "peo",
  "persisch": "per",
  "peul": "ful",
  "phi": "phi",
  "philippine languages": "phi",
  "philippines, langues": "phi",
  "philippinisch-austronesisch (andere)": "phi",
  "phn": "phn",
  "phoenician": "phn",
  "phénicien": "phn",
  "phönikisch": "phn",
  "pi": "pli",
  "pidginsprachen (andere)": "crp",
  "pilipino": "fil",
  "pl": "pol",
  "pli": "pli",
  "pohnpei": "pon",
  "pohnpeian": "pon",
  "pol": "pol",
  "polish": "pol",
  "polnisch": "pol",
  "polonais": "pol",
  "pon": "pon",
  "ponapeanisch": "pon",
  "por": "por",
  "portugais": "por",
  "portugiesisch": "por",
  "portuguese": "por",
  "pra": "pra",
  "prakrit": "pra",
  "prakrit languages": "pra",
  "pro": "pro",
  "provençal ancien (jusqu'à 1500)": "pro",
  "provençal, old": "pro",
  "provençal, old (to 1500)": "pro",
  "prâkrit, langues": "pra",
  "ps": "pus",
  "pt": "por",
  "punjabi": "pan",
  "pus": "pus",
  "pushto": "pus",
  "qaa-qtz": "qaa-qtz",
  "qu": "que",
  "que": "que",
  "quechua": "que",
  "quechua-sprache": "que",
  "raj": "raj",
  "rajasthani": "raj",
  "rap": "rap",
  "rapanui": "rap",
  "rar": "rar",
  "rarotonga": "rar",
  "rarotongan": "rar",
  "rarotonganisch": "rar",
  "reserved for local use": "qaa-qtz",
  "reserviert für lokale verwendung": "qaa-qtz",
  "rm": "roh",
  "rn": "run",
  "ro": "rum",
  "roa": "roa",
  "roh": "roh",
  "rom": "rom",
  "romance languages": "roa",
  "romanche": "roh",
  "romanes, langues": "roa",
  "romani (sprache)": "rom",
  "romanian": "rum",
  "romanische sprachen (andere)": "roa",
  "romansh": "roh",
  "romany": "rom",
  "ron": "rum",
  "rotse-sprache": "loz",
  "roumain": "rum",
  "ru": "rus",
  "rum": "rum",
  "rumänisch": "rum",
  "run": "run",
  "rundi": "run",
  "rundi-sprache": "run",
  "rup": "rup",
  "rus": "rus",
  "russe": "rus",
  "russian": "rus",
  "russisch": "rus",
  "rw": "kin",
  "rwanda": "kin",
  "rwanda-sprache": "kin",
  "rätoromanisch": "roh",
  "réservée à l'usage local": "qaa-qtz",
  "sa": "san",
  "saamisch": "smi",
  "sad": "sad",
  "sag": "sag",
  "sah": "sah",
  "sai": "sai",
  "sakan": "kho",
  "sakisch": "kho",
  "sal": "sal",
  "salish-sprache": "sal",
  "salishan languages": "sal",
  "salishennes, langues": "sal",
  "sam": "sam",
  "samaritain": "sam",
  "samaritan aramaic": "sam",
  "samaritanisch": "sam",
  "sames, langues": "smi",
  "sami d'inari": "smn",
  "sami de lule": "smj",
  "sami du nord": "sme",
  "sami du sud": "sma",
  "sami languages": "smi",
  "sami skolt": "sms",
  "samoan": "smo",
  "samoanisch": "smo",
  "san": "san",
  "sandawe": "sad",
  "sandawe-sprache": "sad",
  "sango": "sag",
  "sango-sprache": "sag",
  "sanskrit": "san",
  "santal": "sat",
  "santali": "sat",
  "sarde": "srd",
  "sardinian": "srd",
  "sardisch": "srd",
  "sas": "sas",
  "sasak": "sas",
  "sat": "sat",
  "saxon, bas": "nds",
  "saxon, low": "nds",
  "sc": "srd",
  "schan-sprache": "shn",
  "schona-sprache": "sna",
  "schottisch": "sco",
  "schwedisch": "swe",
  "schweizerdeutsch": "gsw",
  "scn": "scn",
  "sco": "sco",
  "scots": "sco",
  "scottish gaelic": "gla",
  "sd": "snd",
  "se": "sme",
  "sel": "sel",
  "selkoupe": "sel",
  "selkup": "sel",
  "selkupisch": "sel",
  "sem": "sem",
  "semitic languages": "sem",
  "semitische sprachen (andere)": "sem",
  "sepedi": "nso",
  "serbe": "srp",
  "serbian": "srp",
  "serbisch": "srp",
  "serer": "srr",
  "serer-sprache": "srr",
  "sg": "sag",
  "sga": "sga",
  "sgn": "sgn",
  "shan": "shn",
  "shn": "shn",
  "shona": "sna",
  "si": "sin",
  "sichuan yi": "iii",
  "sicilian": "scn",
  "sicilien": "scn",
  "sid": "sid",
  "sidamo": "sid",
  "sidamo-sprache": "sid",
  "sign languages": "sgn",
  "siksika": "bla",
  "sin": "sin",
  "sindhi": "snd",
  "sindhi-sprache": "snd",
  "singhalais": "sin",
  "singhalesisch": "sin",
  "sinhala": "sin",
  "sinhalese": "sin",
  "sino-tibetan languages": "sit",
  "sino-tibétaines, langues": "sit",
  "sinotibetische sprachen (andere)": "sit",
  "sio": "sio",
  "siouan languages": "sio",
  "sioux, langues": "sio",
  "sioux-sprachen (andere)": "sio",
  "sit": "sit",
  "sizilianisch": "scn",
  "sk": "slo",
  "skolt sami": "sms",
  "skoltsaamisch": "sms",
  "sl": "slv",
  "sla": "sla",
  "slave": "den",
  "slave (athapascan)": "den",
  "slave-sprache": "den",
  "slaves, langues": "sla",
  "slavic languages": "sla",
  "slavon d'église": "chu",
  "slavon liturgique": "chu",
  "slawische sprachen (andere)": "sla",
  "slk": "slo",
  "slo": "slo",
  "slovak": "slo",
  "slovaque": "slo",
  "slovenian": "slv",
  "slovène": "slv",
  "slowakisch": "slo",
  "slowenisch": "slv",
  "slv": "slv",
  "sm": "smo",
  "sma": "sma",
  "sme": "sme",
  "smi": "smi",
  "smj": "smj",
  "smn": "smn",
  "smo": "smo",
  "sms": "sms",
  "sn": "sna",
  "sna": "sna",
  "snd": "snd",
  "snk": "snk",
  "so": "som",
  "sog": "sog",
  "sogdian": "sog",
  "sogdien": "sog",
  "sogdisch": "sog",
  "som": "som",
  "somali": "som",
  "son": "son",
  "songhai languages": "son",
  "songhai, langues": "son",
  "songhai-sprache": "son",
  "soninke": "snk",
  "soninke-sprache": "snk",
  "soninké": "snk",
  "sorabes, langues": "wen",
  "sorbian languages": "wen",
  "sorbisch (andere)": "wen",
  "sot": "sot",
  "sotho du nord": "nso",
  "sotho du sud": "sot",
  "sotho, southern": "sot",
  "soundanais": "sun",
  "soussou": "sus",
  "south american indian languages": "sai",
  "south ndebele": "nbl",
  "southern altai": "alt",
  "southern sami": "sma",
  "spa": "spa",
  "spanisch": "spa",
  "spanish": "spa",
  "sq": "alb",
  "sqi": "alb",
  "sr": "srp",
  "sranan tongo": "srn",
  "sranantongo": "srn",
  "srd": "srd",
  "srn": "srn",
  "srp": "srp",
  "srr": "srr",
  "ss": "ssw",
  "ssa": "ssa",
  "ssw": "ssw",
  "st": "sot",
  "standard moroccan tamazight": "zgh",
  "su": "sun",
  "sud-amérindiennes, langues": "sai",
  "suisse alémanique": "gsw",
  "suk": "suk",
  "sukuma": "suk",
  "sukuma-sprache": "suk",
  "sumerian": "sux",
  "sumerisch": "sux",
  "sumérien": "sux",
  "sun": "sun",
  "sundanese": "sun",
  "sundanesisch": "sun",
  "sus": "sus",
  "susu": "sus",
  "sux": "sux",
  "suédois": "swe",
  "sv": "swe",
  "sw": "swa",
  "swa": "swa",
  "swahili": "swa",
  "swasi-sprache": "ssw",
  "swati": "ssw",
  "swe": "swe",
  "swedish": "swe",
  "swiss german": "gsw",
  "syc": "syc",
  "symboles bliss": "zbl",
  "syr": "syr",
  "syriac": "syr",
  "syriaque": "syr",
  "syriaque classique": "syc",
  "syrisch": "syc",
  "sémitiques, langues": "sem",
  "sérère": "srr",
  "süd-sotho-sprache": "sot",
  "südsaamisch": "sma",
  "ta": "tam",
  "tadjik": "tgk",
  "tadschikisch": "tgk",
  "tagalog": "tgl",
  "tah": "tah",
  "tahitian": "tah",
  "tahitien": "tah",
  "tahitisch": "tah",
  "tai": "tai",
  "tai languages": "tai",
  "tai, langues": "tai",
  "tajik": "tgk",
  "tam": "tam",
  "tamacheq": "tmh",
  "tamashek": "tmh",
  "tamašeq": "tmh",
  "tamil": "tam",
  "tamoul": "tam",
  "tat": "tat",
  "tatar": "tat",
  "tatar de crimé": "crh",
  "tatarisch": "tat",
  "tchouvache": "chv",
  "tchèque": "cze",
  "tchétchène": "che",
  "te": "tel",
  "tel": "tel",
  "telugu": "tel",
  "telugu-sprache": "tel",
  "tem": "tem",
  "temne": "tem",
  "temne-sprache": "tem",
  "ter": "ter",
  "tereno": "ter",
  "tereno-sprache": "ter",
  "tet": "tet",
  "tetum": "tet",
  "tetum-sprache": "tet",
  "tg": "tgk",
  "tgk": "tgk",
  "tgl": "tgl",
  "th": "tha",
  "tha": "tha",
  "thai": "tha",
  "thailändisch": "tha",
  "thaisprachen (andere)": "tai",
  "thaï": "tha",
  "ti": "tir",
  "tib": "tib",
  "tibetan": "tib",
  "tibetisch": "tib",
  "tibétain": "tib",
  "tig": "tig",
  "tigre": "tig",
  "tigre-sprache": "tig",
  "tigrigna": "tir",
  "tigrinja-sprache": "tir",
  "tigrinya": "tir",
  "tigré": "tig",
  "timne": "tem",
  "tir": "tir",
  "tiv": "tiv",
  "tiv-sprache": "tiv",
  "tk": "tuk",
  "tkl": "tkl",
  "tl": "tgl",
  "tlh": "tlh",
  "tlhingan-hol": "tlh",
  "tli": "tli",
  "tlingit": "tli",
  "tlingit-sprache": "tli",
  "tmh": "tmh",
  "tn": "tsn",
  "to": "ton",
  "tog": "tog",
  "tok pisin": "tpi",
  "tokelau": "tkl",
  "tokelauanisch": "tkl",
  "ton": "ton",
  "tonga": "ton",
  "tonga (bantusprache, sambia)": "tog",
  "tonga (nyasa)": "tog",
  "tonga (tonga islands)": "ton",
  "tongaisch": "ton",
  "tongan (îles tonga)": "ton",
  "touva": "tyv",
  "tpi": "tpi",
  "tr": "tur",
  "trukesisch": "chk",
  "ts": "tso",
  "tschagataisch": "chg",
  "tschechisch": "cze",
  "tscheremissisch": "chm",
  "tschetschenisch": "che",
  "tschuwaschisch": "chv",
  "tsi": "tsi",
  "tsigane": "rom",
  "tsimshian": "tsi",
  "tsimshian-sprache": "tsi",
  "tsn": "tsn",
  "tso": "tso",
  "tsonga": "tso",
  "tsonga-sprache": "tso",
  "tswana": "tsn",
  "tswana-sprache": "tsn",
  "tt": "tat",
  "tuk": "tuk",
  "tum": "tum",
  "tumbuka": "tum",
  "tumbuka-sprache": "tum",
  "tup": "tup",
  "tupi languages": "tup",
  "tupi, langues": "tup",
  "tupi-sprache": "tup",
  "tur": "tur",
  "turc": "tur",
  "turc ottoman (1500-1928)": "ota",
  "turkish": "tur",
  "turkish, ottoman": "ota",
  "turkish, ottoman (1500-1928)": "ota",
  "turkmen": "tuk",
  "turkmenisch": "tuk",
  "turkmène": "tuk",
  "tut": "tut",
  "tuvalu": "tvl",
  "tuvinian": "tyv",
  "tuwinisch": "tyv",
  "tvl": "tvl",
  "tw": "twi",
  "twi": "twi",
  "twi-sprache": "twi",
  "ty": "tah",
  "tyv": "tyv",
  "télougou": "tel",
  "türkisch": "tur",
  "udm": "udm",
  "udmurt": "udm",
  "udmurtisch": "udm",
  "ug": "uig",
  "uga": "uga",
  "ugaritic": "uga",
  "ugaritisch": "uga",
  "uig": "uig",
  "uighur": "uig",
  "uigurisch": "uig",
  "uk": "ukr",
  "ukr": "ukr",
  "ukrainian": "ukr",
  "ukrainien": "ukr",
  "ukrainisch": "ukr",
  "umb": "umb",
  "umbundu": "umb",
  "uncoded languages": "mis",
  "und": "und",
  "undetermined": "und",
  "ungarisch": "hun",
  "upper sorbian": "hsb",
  "ur": "urd",
  "urd": "urd",
  "urdu": "urd",
  "usbekisch": "uzb",
  "uyghur": "uig",
  "uz": "uzb",
  "uzb": "uzb",
  "uzbek": "uzb",
  "vai": "vai",
  "vai-sprache": "vai",
  "valencian": "cat",
  "valencien": "cat",
  "vaï": "vai",
  "ve": "ven",
  "ven": "ven",
  "venda": "ven",
  "venda-sprache": "ven",
  "vi": "vie",
  "vie": "vie",
  "vietnamese": "vie",
  "vietnamesisch": "vie",
  "vietnamien": "vie",
  "vieux bulgare": "chu",
  "vieux slave": "chu",
  "vo": "vol",
  "vol": "vol",
  "volapük": "vol",
  "vot": "vot",
  "vote": "vot",
  "votic": "vot",
  "wa": "wln",
  "wak": "wak",
  "wakash-sprachen": "wak",
  "wakashan languages": "wak",
  "wakashanes, langues": "wak",
  "wal": "wal",
  "walamo-sprache": "wal",
  "wallon": "wln",
  "wallonisch": "wln",
  "walloon": "wln",
  "war": "war",
  "waray": "war",
  "was": "was",
  "washo": "was",
  "washo-sprache": "was",
  "weißrussisch": "bel",
  "wel": "wel",
  "welsh": "wel",
  "wen": "wen",
  "western frisian": "fry",
  "western pahari languages": "him",
  "wln": "wln",
  "wo": "wol",
  "wol": "wol",
  "wolaitta": "wal",
  "wolaytta": "wal",
  "wolof": "wol",
  "wolof-sprache": "wol",
  "wotisch": "vot",
  "xal": "xal",
  "xh": "xho",
  "xho": "xho",
  "xhosa": "xho",
  "xhosa-sprache": "xho",
  "yakut": "sah",
  "yao": "yao",
  "yao-sprache (bantusprache)": "yao",
  "yap": "yap",
  "yapese": "yap",
  "yapesisch": "yap",
  "yapois": "yap",
  "yi": "yid",
  "yi de sichuan": "iii",
  "yid": "yid",
  "yiddish": "yid",
  "yo": "yor",
  "yor": "yor",
  "yoruba": "yor",
  "yoruba-sprache": "yor",
  "ypik-sprachen": "ypk",
  "ypk": "ypk",
  "yupik languages": "ypk",
  "yupik, langues": "ypk",
  "za": "zha",
  "zande languages": "znd",
  "zande-sprachen": "znd",
  "zandé, langues": "znd",
  "zap": "zap",
  "zapotec": "zap",
  "zapotekisch": "zap",
  "zapotèque": "zap",
  "zaza": "zza",
  "zazaki": "zza",
  "zbl": "zbl",
  "zeichensprachen": "sgn",
  "zen": "zen",
  "zenaga": "zen",
  "zgh": "zgh",
  "zh": "chi",
  "zha": "zha",
  "zho": "chi",
  "zhuang": "zha",
  "znd": "znd",
  "zoulou": "zul",
  "zu": "zul",
  "zul": "zul",
  "zulu": "zul",
  "zulu-sprache": "zul",
  "zun": "zun",
  "zuni": "zun",
  "zuñi-sprache": "zun",
  "zxx": "zxx",
  "zza": "zza",
  "ägyptisch": "egy",
  "écossais": "sco",
  "égyptien": "egy",
  "élamite": "elx",
  "éwondo": "ewo",
  "éwé": "ewe"
}
